wj_pytrends/.gitignore
wj_pytrends/__init__.py
wj_pytrends/dailydata.py
wj_pytrends/exceptions.py
wj_pytrends/request.py
wj_pytrends/test_trendReq.py
wj_pytrends-1.0.5.dist-info/LICENSE.md
wj_pytrends-1.0.5.dist-info/WHEEL
wj_pytrends-1.0.5.dist-info/METADATA
wj_pytrends-1.0.5.dist-info/RECORD
